hazard_map/__init__.py
hazard_map/hazard_map.py
hazard_map-0.3.0.dist-info/METADATA
hazard_map-0.3.0.dist-info/WHEEL
hazard_map-0.3.0.dist-info/entry_points.txt
hazard_map-0.3.0.dist-info/RECORD
