Metadata-Version: 2.1
Name: hazard-map
Version: 0.3.0
Summary: Build and analyze a network model of hazards, causes, and controls
License: license.txt
Author: Thom Cameron
Author-email: thomcm@proton.me
Requires-Python: >=3.11,<4.0
Classifier: License :: Other/Proprietary License
Classifier: Programming Language :: Python :: 3
Classifier: Programming Language :: Python :: 3.11
Classifier: Programming Language :: Python :: 3.12
Requires-Dist: argparse (>=1.4,<2.0)
Requires-Dist: matplotlib (>=3.8,<4.0)
Requires-Dist: networkx (>=3.3,<4.0)
Requires-Dist: numpy (>=1.26,<2.0)
Requires-Dist: openpyxl (>=3.1,<4.0)
Requires-Dist: pandas (>=2.2,<3.0)
Requires-Dist: scipy (>=1.13,<2.0)
Requires-Dist: termcolor (>=2.4,<3.0)
